draftsman/__init__.py
draftsman/_version.py
draftsman/blueprintable.py
draftsman/constants.py
draftsman/entity.py
draftsman/error.py
draftsman/extras.py
draftsman/rail.py
draftsman/serialization.py
draftsman/signatures.py
draftsman/tile.py
draftsman/types.py
draftsman/utils.py
draftsman/validators.py
draftsman/warning.py
draftsman/classes/__init__.py
draftsman/classes/association.py
draftsman/classes/blueprint.py
draftsman/classes/blueprint_book.py
draftsman/classes/blueprintable.py
draftsman/classes/collection.py
draftsman/classes/collision_set.py
draftsman/classes/deconstruction_planner.py
draftsman/classes/entity.py
draftsman/classes/entity_like.py
draftsman/classes/entity_list.py
draftsman/classes/exportable.py
draftsman/classes/group.py
draftsman/classes/rail_planner.py
draftsman/classes/schedule.py
draftsman/classes/schedule_list.py
draftsman/classes/spatial_data_structure.py
draftsman/classes/spatial_hashmap.py
draftsman/classes/spatial_like.py
draftsman/classes/tile.py
draftsman/classes/tile_list.py
draftsman/classes/train_configuration.py
draftsman/classes/transformable.py
draftsman/classes/upgrade_planner.py
draftsman/classes/vector.py
draftsman/classes/mixins/__init__.py
draftsman/classes/mixins/artillery_auto_target.py
draftsman/classes/mixins/circuit_condition.py
draftsman/classes/mixins/circuit_connectable.py
draftsman/classes/mixins/circuit_enable.py
draftsman/classes/mixins/circuit_read_contents.py
draftsman/classes/mixins/circuit_read_hand.py
draftsman/classes/mixins/circuit_read_resource.py
draftsman/classes/mixins/circuit_set_filters.py
draftsman/classes/mixins/color.py
draftsman/classes/mixins/control_behavior.py
draftsman/classes/mixins/crafting_machine.py
draftsman/classes/mixins/directional.py
draftsman/classes/mixins/energy_source.py
draftsman/classes/mixins/equipment_grid.py
draftsman/classes/mixins/filters.py
draftsman/classes/mixins/input_ingredients.py
draftsman/classes/mixins/inventory.py
draftsman/classes/mixins/io_type.py
factorio_draftsman-3.2.0.dist-info/licenses/LICENSE
factorio_draftsman-3.2.0.dist-info/METADATA
factorio_draftsman-3.2.0.dist-info/WHEEL
factorio_draftsman-3.2.0.dist-info/entry_points.txt
factorio_draftsman-3.2.0.dist-info/top_level.txt
factorio_draftsman-3.2.0.dist-info/RECORD
