Metadata-Version: 2.4
Name: factorio-draftsman
Version: 3.2.0
Summary: A complete, well-tested, and up-to-date module to manipulate Factorio blueprint strings. Compatible with mods.
Author: redruin01
License-Expression: MIT
Project-URL: Homepage, https://github.com/redruin1/factorio-draftsman
Project-URL: Documentation, https://factorio-draftsman.readthedocs.io/en/latest/index.html
Project-URL: Issues, https://github.com/redruin1/factorio-draftsman/issues
Project-URL: Changelog, https://github.com/redruin1/factorio-draftsman/blob/main/changelog.md
Keywords: factorio,blueprint,string
Classifier: Development Status :: 4 - Beta
Classifier: Programming Language :: Python :: 3.10
Classifier: Programming Language :: Python :: 3.11
Classifier: Programming Language :: Python :: 3.12
Classifier: Programming Language :: Python :: 3.13
Classifier: Intended Audience :: Developers
Classifier: Intended Audience :: End Users/Desktop
Classifier: Operating System :: OS Independent
Requires-Python: >=3.9
License-File: LICENSE
Requires-Dist: attrs>=25.4.0
Requires-Dist: cattrs>=24.1.3
Requires-Dist: lupa>=2.0
Requires-Dist: GitPython>=3.1.43
Requires-Dist: thefuzz>=0.20.0
Requires-Dist: enum_tools>=0.13.0
Requires-Dist: typing
Requires-Dist: typing_extensions; python_version < "3.8"
Dynamic: license-file
